pickson/__init__.py
pickson/pickson.py
pickson-1.0.4.dist-info/LICENSE
pickson-1.0.4.dist-info/METADATA
pickson-1.0.4.dist-info/WHEEL
pickson-1.0.4.dist-info/top_level.txt
pickson-1.0.4.dist-info/RECORD
